govuk_frontend_wtf/__init__.py
govuk_frontend_wtf/gov_form_base.py
govuk_frontend_wtf/main.py
govuk_frontend_wtf/wtforms_widgets.py
govuk_frontend_wtf/templates/button.html
govuk_frontend_wtf/templates/charactercount.html
govuk_frontend_wtf/templates/checkboxes.html
govuk_frontend_wtf/templates/date.html
govuk_frontend_wtf/templates/file-upload.html
govuk_frontend_wtf/templates/input.html
govuk_frontend_wtf/templates/password.html
govuk_frontend_wtf/templates/radios.html
govuk_frontend_wtf/templates/select.html
govuk_frontend_wtf/templates/textarea.html
govuk_frontend_wtf-3.2.0.dist-info/LICENSE
govuk_frontend_wtf-3.2.0.dist-info/METADATA
govuk_frontend_wtf-3.2.0.dist-info/WHEEL
govuk_frontend_wtf-3.2.0.dist-info/top_level.txt
govuk_frontend_wtf-3.2.0.dist-info/RECORD
