Metadata-Version: 2.1
Name: govuk-frontend-wtf
Version: 3.2.0
Summary: GOV.UK Frontend WTForms Widgets
Home-page: https://github.com/LandRegistry/govuk-frontend-wtf
Author: Matt Shaw
Author-email: matthew.shaw@landregistry.gov.uk
Classifier: Development Status :: 5 - Production/Stable
Classifier: Environment :: Web Environment
Classifier: Intended Audience :: Developers
Classifier: License :: OSI Approved :: MIT License
Classifier: Operating System :: OS Independent
Classifier: Programming Language :: Python :: 3.10
Classifier: Programming Language :: Python :: 3.11
Classifier: Programming Language :: Python :: 3.12
Classifier: Programming Language :: Python :: 3.13
Classifier: Programming Language :: Python :: 3.9
Classifier: Topic :: Software Development :: Code Generators
Classifier: Topic :: Software Development :: User Interfaces
Classifier: Topic :: Text Processing :: Markup :: HTML
Requires-Python: >=3.9
License-File: LICENSE
Requires-Dist: deepmerge
Requires-Dist: flask
Requires-Dist: flask-wtf
Requires-Dist: govuk-frontend-jinja >=3.0.0
Requires-Dist: jinja2
Requires-Dist: wtforms >=3.1.0
